mdg/__init__.py
mdg/config.py
mdg/generate/__init__.py
mdg/generate/render.py
mdg/generate/confluence/__init__.py
mdg/generate/confluence/content_update.py
mdg/generate/confluence/image_update.py
mdg/generate/confluence/util.py
mdg/parse/__init__.py
mdg/parse/bouml_xmi.py
mdg/parse/drawio_xml.py
mdg/parse/erwin_xmi.py
mdg/parse/excel.py
mdg/parse/marmaid.py
mdg/parse/sparx_db.py
mdg/parse/sparx_db_models.py
mdg/parse/sparx_xmi.py
mdg/templates/base.txt.jinja
mdg/templates/hasura-abac.json.jinja
mdg/templates/hasura.json.jinja
mdg/templates/postgresql.sql.jinja
mdg/templates/Arango/models.py.jinja
mdg/templates/Django/manage.py.jinja
mdg/templates/Django/requirements.txt.jinja
mdg/templates/Django/.azure/config.jinja
mdg/templates/Django/.azure/setup.ps1.jinja
mdg/templates/Django/app/__init__.py
mdg/templates/Django/app/__init__.py.jinja
mdg/templates/Django/app/admin.py.jinja
mdg/templates/Django/app/apps.py.jinja
mdg/templates/Django/app/models.py.jinja
mdg/templates/Django/app/serializers.py.jinja
mdg/templates/Django/app/urls.py.jinja
mdg/templates/Django/app/views.py.jinja
mdg/templates/Django/project/__init__.py
mdg/templates/Django/project/asgi.py.jinja
mdg/templates/Django/project/settings.py.jinja
mdg/templates/Django/project/urls.py.jinja
mdg/templates/Django/project/validators.py.jinja
mdg/templates/Django/project/views.py
mdg/templates/Django/project/wsgi.py.jinja
mdg/templates/Java/entities.jdl.jinja
mdg/templates/Java/enums.java.jinja
mdg/templates/Java/pojos.java.jinja
mdg/templates/Python/dataclass_avro.py.jinja
mdg/templates/SQLAlchemy/models.py.jinja
mdg/templates/SQLAlchemy/schemas.py.jinja
mdg/templates/Schema/asyncapi.yaml.jinja
mdg/templates/Schema/avro.avsc.jinja
mdg/templates/Schema/openapi.yaml.jinja
mdg/tests/__init__.py
mdg/tests/test_dumps.py
mdg/tests/test_instance.py
mdg/tests/test_parse_sparx_db.py
mdg/tests/test_parse_sparx_xmi.py
mdg/tests/test_sample.py
mdg/tests/test_tools.py
mdg/tests/test_uml_model.py
pymdg-1.2.6.dist-info/licenses/LICENSE
pymdg-1.2.6.dist-info/METADATA
pymdg-1.2.6.dist-info/WHEEL
pymdg-1.2.6.dist-info/entry_points.txt
pymdg-1.2.6.dist-info/top_level.txt
pymdg-1.2.6.dist-info/RECORD
