Metadata-Version: 2.4
Name: pymdg
Version: 1.2.6
Summary: Model driven genration - from UML to Code & Docs
Home-page: https://github.com/semprini/pyMDG
Author: Semprini
Author-email: dont@contact.me
Classifier: Programming Language :: Python :: 3
Classifier: License :: OSI Approved :: GNU General Public License (GPL)
Classifier: Operating System :: OS Independent
Requires-Python: >=3.11
License-File: LICENSE
Requires-Dist: lxml
Requires-Dist: jinja2
Requires-Dist: pyyaml
Requires-Dist: sqlalchemy
Dynamic: author
Dynamic: author-email
Dynamic: classifier
Dynamic: description
Dynamic: description-content-type
Dynamic: home-page
Dynamic: license-file
Dynamic: requires-dist
Dynamic: requires-python
Dynamic: summary
